drafty/__init__.py
drafty-2025.0.0.dist-info/WHEEL
drafty-2025.0.0.dist-info/METADATA
drafty-2025.0.0.dist-info/RECORD
