Metadata-Version: 2.3
Name: drafty
Version: 2025.0.0
Summary: Blue Prince drafting assistant
Author: Blake Naccarato
Author-email: Blake Naccarato <blake.naccarato@gmail.com>
License: MIT License
Classifier: License :: OSI Approved :: MIT License
Classifier: Programming Language :: Python :: 3.11
Classifier: Programming Language :: Python :: 3.12
Requires-Python: >=3.11
Project-URL: Changes, https://blakeNaccarato.github.io/drafty/changelog.html
Project-URL: Docs, https://blakeNaccarato.github.io/drafty
Project-URL: Home, https://github.com/blakeNaccarato/drafty
Project-URL: Tracker, https://github.com/blakeNaccarato/drafty/issues
